myrient.py
myrient_downloader_cli-0.4.0.dist-info/licenses/LICENSE
myrient_downloader_cli-0.4.0.dist-info/METADATA
myrient_downloader_cli-0.4.0.dist-info/WHEEL
myrient_downloader_cli-0.4.0.dist-info/entry_points.txt
myrient_downloader_cli-0.4.0.dist-info/top_level.txt
myrient_downloader_cli-0.4.0.dist-info/RECORD
