Metadata-Version: 2.4
Name: myrient-downloader-cli
Version: 0.4.0
License-File: LICENSE
Requires-Dist: requests==2.32.3
Requires-Dist: beautifulsoup4==4.13.4
Requires-Dist: textual==6.7.1
Dynamic: license-file
Dynamic: requires-dist
